Workbook

Sheet CurrentPor-Equ Factor Movements
C1: LH = 10 | G1: LH = 20 | H1: LH = 40 | I1: LH = 60 | J1: LH = 20 | K1: Standard deviation of factors
A2: DATE | C2: 1Y_Treasury | D2: 2Y_Treasury | E2: MSFT price | F2: Intel price | G2: Credit spread: sovereign (investment grade, or IG) | H2: Credit spread: sovereign (high yield, or HY) | I2: Credit Spread: Corporate(HY) | J2: Carbon Credits | K2: 1Y_Treasury | L2: 2Y_Treasury | M2: MSFT price | N2: Intel price | O2: Credit spread: sovereign (investment grade, or IG) | P2: Credit spread: sovereign (high yield, or HY) | Q2: Credit Spread: Corporate(HY) | R2: Carbon Credits
A3: 45474 | B3: 45474 | C3: 4.2673967 | D3: 4.5673967 | E3: 530.0671 | F3: 38.486313 | G3: 0.51 | H3: 0.58622522 | I3: 0.69637381 | J3: 21.480999 | K3: =_xlfn.STDEV.P(C3:C263) -> 2.6645353e-15 | L3: =_xlfn.STDEV.P(D3:D263) -> 6.2172489e-15 | M3: =_xlfn.STDEV.P(E3:E263) -> 9.9207534 | N3: =_xlfn.STDEV.P(F3:F263) -> 1.8919904 | O3: =_xlfn.STDEV.P(G3:G263) -> 1.7763568e-15 | P3: =_xlfn.STDEV.P(H3:H263) -> 1.8873791e-15 | Q3: =_xlfn.STDEV.P(I3:I263) -> 3.663736e-15 | R3: =_xlfn.STDEV.P(J3:J263) -> 6.750156e-14
A4: 45475 | B4: 45475 | C4: 4.2673967 | D4: 4.5673967 | E4: 522.828 | F4: 35.525856 | G4: 0.51 | H4: 0.58622522 | I4: 0.69637381 | J4: 21.480999 | K4: Standard deviation/Average%
A5: 45476 | B5: 45476 | C5: 4.2673967 | D5: 4.5673967 | E5: 510.1185 | F5: 36.378868 | G5: 0.51 | H5: 0.58622522 | I5: 0.69637381 | J5: 21.480999 | K5: =_xlfn.STDEV.P(C3:C263)/AVERAGE(C3:C263) -> 6.2439362e-16 | L5: =_xlfn.STDEV.P(D3:D263)/AVERAGE(D3:D263) -> 1.3612238e-15 | M5: =_xlfn.STDEV.P(E3:E263)/AVERAGE(E3:E263) -> 0.019026416 | N5: =_xlfn.STDEV.P(F3:F263)/AVERAGE(F3:F263) -> 0.053110693 | O5: =_xlfn.STDEV.P(G3:G263)/AVERAGE(G3:G263) -> 3.4830526e-15 | P5: =_xlfn.STDEV.P(H3:H263)/AVERAGE(H3:H263) -> 3.2195461e-15 | Q5: =_xlfn.STDEV.P(I3:I263)/AVERAGE(I3:I263) -> 5.2611628e-15 | R5: =_xlfn.STDEV.P(J3:J263)/AVERAGE(J3:J263) -> 3.1423846e-15
A6: 45477 | B6: 45477 | C6: 4.2673967 | D6: 4.5673967 | E6: 516.68968 | F6: 36.138276 | G6: 0.51 | H6: 0.58622522 | I6: 0.69637381 | J6: 21.480999
A7: 45478 | B7: 45478 | C7: 4.2673967 | D7: 4.5673967 | E7: 511.90516 | F7: 35.611754 | G7: 0.51 | H7: 0.58622522 | I7: 0.69637381 | J7: 21.480999
A8: 45481 | B8: 45481 | C8: 4.2673967 | D8: 4.5673967 | E8: 513.45231 | F8: 37.709248 | G8: 0.51 | H8: 0.58622522 | I8: 0.69637381 | J8: 21.480999
A9: 45482 | B9: 45482 | C9: 4.2673967 | D9: 4.5673967 | E9: 519.33854 | F9: 36.256978 | G9: 0.51 | H9: 0.58622522 | I9: 0.69637381 | J9: 21.480999
A10: 45483 | B10: 45483 | C10: 4.2673967 | D10: 4.5673967 | E10: 515.82192 | F10: 35.112746 | G10: 0.51 | H10: 0.58622522 | I10: 0.69637381 | J10: 21.480999
A11: 45484 | B11: 45484 | C11: 4.2673967 | D11: 4.5673967 | E11: 529.18295 | F11: 35.866392 | G11: 0.51 | H11: 0.58622522 | I11: 0.69637381 | J11: 21.480999
A12: 45485 | B12: 45485 | C12: 4.2673967 | D12: 4.5673967 | E12: 528.77176 | F12: 34.84045 | G12: 0.51 | H12: 0.58622522 | I12: 0.69637381 | J12: 21.480999
A13: 45488 | B13: 45488 | C13: 4.2673967 | D13: 4.5673967 | E13: 509.46564 | F13: 38.812221 | G13: 0.51 | H13: 0.58622522 | I13: 0.69637381 | J13: 21.480999
A14: 45489 | B14: 45489 | C14: 4.2673967 | D14: 4.5673967 | E14: 544.08626 | F14: 36.566971 | G14: 0.51 | H14: 0.58622522 | I14: 0.69637381 | J14: 21.480999
A15: 45490 | B15: 45490 | C15: 4.2673967 | D15: 4.5673967 | E15: 539.48766 | F15: 33.921065 | G15: 0.51 | H15: 0.58622522 | I15: 0.69637381 | J15: 21.480999
A16: 45491 | B16: 45491 | C16: 4.2673967 | D16: 4.5673967 | E16: 526.4721 | F16: 38.70626 | G16: 0.51 | H16: 0.58622522 | I16: 0.69637381 | J16: 21.480999
A17: 45492 | B17: 45492 | C17: 4.2673967 | D17: 4.5673967 | E17: 520.06071 | F17: 36.498394 | G17: 0.51 | H17: 0.58622522 | I17: 0.69637381 | J17: 21.480999
... A263: 45838 | B263: 45838 | C263: 4.2673967 | D263: 4.5673967 | E263: 510.79332 | F263: 36.152701 | G263: 0.51 | H263: 0.58622522 | I263: 0.69637381 | J263: 21.480999

Sheet Portfolio
A1: Holding | B1: Quantity | C1: Coupon | D1: Notional | E1: Price | F1: Total | J1: T | N1: LH | O1: ES | P1: Absolute ES | Q1: Calculated value
A2: Treasury bonds | B2: 100 | C2: 3 | D2: 100 | F2: =B2*D2 -> 10000 | J2: 10 | M2: EST(P) | N2: 10 | O2: ='ES, Equity factor movement'!L3 -> -3198.6681 | P2: =ABS(O2) -> 3198.6681 | Q2: =P2*P2 -> 10231478
A3: Sovereign Bonds HY | B3: 100 | C3: 3 | D3: 100 | F3: =B3*D3 -> 10000 | P3: ESF,C | Q3: =SQRT(SUM(Q2:Q2)) -> 3198.6681
A4: Sovereign Bonds IG | B4: 100 | C4: 3 | D4: 100 | F4: =B4*D4 -> 10000
A5: MSFT stocks | B5: 100 | E5: 500 | F5: =B5*E5 -> 50000
A6: Intel Stock | B6: 100 | E6: 36 | F6: =B6*E6 -> 3600
A7: Carbon credits | B7: 100 | E7: 20 | F7: =B7*E7 -> 2000
A8: Credit Spread Corporate HY | B8: 100 | C8: 3 | D8: 100 | F8: =B8*D8 -> 10000
F9: =SUM(F2:F8) -> 95600

Sheet ES, Equity factor movement
B1: LH=10 | C1: LH=10, 20 | D1: LH=10, 40 | E1: LH=10, 60 | F1: LH=10 | G1: LH=10 | H1: LH=20
B2: Treasury Bonds IG valuation | C2: Credit spread: Sovereign Bonds IG valuation | D2: Credit spread: sovereign (high yield, or HY) | E2: Credit Spread:Corporate HY | F2: MSFT | G2: Intel | H2: carbon credits | I2: Portfolio value | J2: 10 day PnL | K2: VaR | L2: ES, Q(pi,1)
A3: 45474 | B3: =(3/(1+('CurrentPor-Equ Factor Movements'!C3)/100)+103/POWER(1+('CurrentPor-Equ Factor Movements'!D3)/100,2))*100 -> 9707.5858 | C3: =(3/(1+('CurrentPor-Equ Factor Movements'!C3+'CurrentPor-Equ Factor Movements'!G3)/100)+103/POWER(1+('CurrentPor-Equ Factor Movements'!D3+'CurrentPor-Equ Factor Movements'!G3)/100,2))*100 -> 9614.9674 | D3: =(3/(1+('CurrentPor-Equ Factor Movements'!C3+'CurrentPor-Equ Factor Movements'!H3)/100)+103/POWER(1+('CurrentPor-Equ Factor Movements'!D3+'CurrentPor-Equ Factor Movements'!H3)/100,2))*100 -> 9601.2396 | E3: =(3/(1+('CurrentPor-Equ Factor Movements'!C3+'CurrentPor-Equ Factor Movements'!I3)/100)+103/POWER(1+('CurrentPor-Equ Factor Movements'!D3+'CurrentPor-Equ Factor Movements'!I3)/100,2))*100 -> 9581.4547 | F3: =Portfolio!B$5*'CurrentPor-Equ Factor Movements'!E3 -> 53006.71 | G3: =Portfolio!B$6*'CurrentPor-Equ Factor Movements'!F3 -> 3848.6313 | H3: =Portfolio!B$7*'CurrentPor-Equ Factor Movements'!J3 -> 2148.0999 | I3: =SUM(B3:H3) -> 97508.689 | K3: =_xlfn.PERCENTILE.INC(J13:J263, 0.025) -> -2757.7393 | L3: =AVERAGEIF(J13:J263, "<="&K3,J13:J263) -> -3198.6681
A4: 45475 | B4: =(3/(1+('CurrentPor-Equ Factor Movements'!C4)/100)+103/POWER(1+('CurrentPor-Equ Factor Movements'!D4)/100,2))*100 -> 9707.5858 | C4: =(3/(1+('CurrentPor-Equ Factor Movements'!C4+'CurrentPor-Equ Factor Movements'!G4)/100)+103/POWER(1+('CurrentPor-Equ Factor Movements'!D4+'CurrentPor-Equ Factor Movements'!G4)/100,2))*100 -> 9614.9674 | D4: =(3/(1+('CurrentPor-Equ Factor Movements'!C4+'CurrentPor-Equ Factor Movements'!H4)/100)+103/POWER(1+('CurrentPor-Equ Factor Movements'!D4+'CurrentPor-Equ Factor Movements'!H4)/100,2))*100 -> 9601.2396 | E4: =(3/(1+('CurrentPor-Equ Factor Movements'!C4+'CurrentPor-Equ Factor Movements'!I4)/100)+103/POWER(1+('CurrentPor-Equ Factor Movements'!D4+'CurrentPor-Equ Factor Movements'!I4)/100,2))*100 -> 9581.4547 | F4: =Portfolio!B$5*'CurrentPor-Equ Factor Movements'!E4 -> 52282.8 | G4: =Portfolio!B$6*'CurrentPor-Equ Factor Movements'!F4 -> 3552.5856 | H4: =Portfolio!B$7*'CurrentPor-Equ Factor Movements'!J4 -> 2148.0999 | I4: =SUM(B4:H4) -> 96488.733
A5: 45476 | B5: =(3/(1+('CurrentPor-Equ Factor Movements'!C5)/100)+103/POWER(1+('CurrentPor-Equ Factor Movements'!D5)/100,2))*100 -> 9707.5858 | C5: =(3/(1+('CurrentPor-Equ Factor Movements'!C5+'CurrentPor-Equ Factor Movements'!G5)/100)+103/POWER(1+('CurrentPor-Equ Factor Movements'!D5+'CurrentPor-Equ Factor Movements'!G5)/100,2))*100 -> 9614.9674 | D5: =(3/(1+('CurrentPor-Equ Factor Movements'!C5+'CurrentPor-Equ Factor Movements'!H5)/100)+103/POWER(1+('CurrentPor-Equ Factor Movements'!D5+'CurrentPor-Equ Factor Movements'!H5)/100,2))*100 -> 9601.2396 | E5: =(3/(1+('CurrentPor-Equ Factor Movements'!C5+'CurrentPor-Equ Factor Movements'!I5)/100)+103/POWER(1+('CurrentPor-Equ Factor Movements'!D5+'CurrentPor-Equ Factor Movements'!I5)/100,2))*100 -> 9581.4547 | F5: =Portfolio!B$5*'CurrentPor-Equ Factor Movements'!E5 -> 51011.85 | G5: =Portfolio!B$6*'CurrentPor-Equ Factor Movements'!F5 -> 3637.8868 | H5: =Portfolio!B$7*'CurrentPor-Equ Factor Movements'!J5 -> 2148.0999 | I5: =SUM(B5:H5) -> 95303.084
A6: 45477 | B6: =(3/(1+('CurrentPor-Equ Factor Movements'!C6)/100)+103/POWER(1+('CurrentPor-Equ Factor Movements'!D6)/100,2))*100 -> 9707.5858 | C6: =(3/(1+('CurrentPor-Equ Factor Movements'!C6+'CurrentPor-Equ Factor Movements'!G6)/100)+103/POWER(1+('CurrentPor-Equ Factor Movements'!D6+'CurrentPor-Equ Factor Movements'!G6)/100,2))*100 -> 9614.9674 | D6: =(3/(1+('CurrentPor-Equ Factor Movements'!C6+'CurrentPor-Equ Factor Movements'!H6)/100)+103/POWER(1+('CurrentPor-Equ Factor Movements'!D6+'CurrentPor-Equ Factor Movements'!H6)/100,2))*100 -> 9601.2396 | E6: =(3/(1+('CurrentPor-Equ Factor Movements'!C6+'CurrentPor-Equ Factor Movements'!I6)/100)+103/POWER(1+('CurrentPor-Equ Factor Movements'!D6+'CurrentPor-Equ Factor Movements'!I6)/100,2))*100 -> 9581.4547 | F6: =Portfolio!B$5*'CurrentPor-Equ Factor Movements'!E6 -> 51668.968 | G6: =Portfolio!B$6*'CurrentPor-Equ Factor Movements'!F6 -> 3613.8276 | H6: =Portfolio!B$7*'CurrentPor-Equ Factor Movements'!J6 -> 2148.0999 | I6: =SUM(B6:H6) -> 95936.143
A7: 45478 | B7: =(3/(1+('CurrentPor-Equ Factor Movements'!C7)/100)+103/POWER(1+('CurrentPor-Equ Factor Movements'!D7)/100,2))*100 -> 9707.5858 | C7: =(3/(1+('CurrentPor-Equ Factor Movements'!C7+'CurrentPor-Equ Factor Movements'!G7)/100)+103/POWER(1+('CurrentPor-Equ Factor Movements'!D7+'CurrentPor-Equ Factor Movements'!G7)/100,2))*100 -> 9614.9674 | D7: =(3/(1+('CurrentPor-Equ Factor Movements'!C7+'CurrentPor-Equ Factor Movements'!H7)/100)+103/POWER(1+('CurrentPor-Equ Factor Movements'!D7+'CurrentPor-Equ Factor Movements'!H7)/100,2))*100 -> 9601.2396 | E7: =(3/(1+('CurrentPor-Equ Factor Movements'!C7+'CurrentPor-Equ Factor Movements'!I7)/100)+103/POWER(1+('CurrentPor-Equ Factor Movements'!D7+'CurrentPor-Equ Factor Movements'!I7)/100,2))*100 -> 9581.4547 | F7: =Portfolio!B$5*'CurrentPor-Equ Factor Movements'!E7 -> 51190.516 | G7: =Portfolio!B$6*'CurrentPor-Equ Factor Movements'!F7 -> 3561.1754 | H7: =Portfolio!B$7*'CurrentPor-Equ Factor Movements'!J7 -> 2148.0999 | I7: =SUM(B7:H7) -> 95405.038
A8: 45481 | B8: =(3/(1+('CurrentPor-Equ Factor Movements'!C8)/100)+103/POWER(1+('CurrentPor-Equ Factor Movements'!D8)/100,2))*100 -> 9707.5858 | C8: =(3/(1+('CurrentPor-Equ Factor Movements'!C8+'CurrentPor-Equ Factor Movements'!G8)/100)+103/POWER(1+('CurrentPor-Equ Factor Movements'!D8+'CurrentPor-Equ Factor Movements'!G8)/100,2))*100 -> 9614.9674 | D8: =(3/(1+('CurrentPor-Equ Factor Movements'!C8+'CurrentPor-Equ Factor Movements'!H8)/100)+103/POWER(1+('CurrentPor-Equ Factor Movements'!D8+'CurrentPor-Equ Factor Movements'!H8)/100,2))*100 -> 9601.2396 | E8: =(3/(1+('CurrentPor-Equ Factor Movements'!C8+'CurrentPor-Equ Factor Movements'!I8)/100)+103/POWER(1+('CurrentPor-Equ Factor Movements'!D8+'CurrentPor-Equ Factor Movements'!I8)/100,2))*100 -> 9581.4547 | F8: =Portfolio!B$5*'CurrentPor-Equ Factor Movements'!E8 -> 51345.231 | G8: =Portfolio!B$6*'CurrentPor-Equ Factor Movements'!F8 -> 3770.9248 | H8: =Portfolio!B$7*'CurrentPor-Equ Factor Movements'!J8 -> 2148.0999 | I8: =SUM(B8:H8) -> 95769.504
A9: 45482 | B9: =(3/(1+('CurrentPor-Equ Factor Movements'!C9)/100)+103/POWER(1+('CurrentPor-Equ Factor Movements'!D9)/100,2))*100 -> 9707.5858 | C9: =(3/(1+('CurrentPor-Equ Factor Movements'!C9+'CurrentPor-Equ Factor Movements'!G9)/100)+103/POWER(1+('CurrentPor-Equ Factor Movements'!D9+'CurrentPor-Equ Factor Movements'!G9)/100,2))*100 -> 9614.9674 | D9: =(3/(1+('CurrentPor-Equ Factor Movements'!C9+'CurrentPor-Equ Factor Movements'!H9)/100)+103/POWER(1+('CurrentPor-Equ Factor Movements'!D9+'CurrentPor-Equ Factor Movements'!H9)/100,2))*100 -> 9601.2396 | E9: =(3/(1+('CurrentPor-Equ Factor Movements'!C9+'CurrentPor-Equ Factor Movements'!I9)/100)+103/POWER(1+('CurrentPor-Equ Factor Movements'!D9+'CurrentPor-Equ Factor Movements'!I9)/100,2))*100 -> 9581.4547 | F9: =Portfolio!B$5*'CurrentPor-Equ Factor Movements'!E9 -> 51933.854 | G9: =Portfolio!B$6*'CurrentPor-Equ Factor Movements'!F9 -> 3625.6978 | H9: =Portfolio!B$7*'CurrentPor-Equ Factor Movements'!J9 -> 2148.0999 | I9: =SUM(B9:H9) -> 96212.899
A10: 45483 | B10: =(3/(1+('CurrentPor-Equ Factor Movements'!C10)/100)+103/POWER(1+('CurrentPor-Equ Factor Movements'!D10)/100,2))*100 -> 9707.5858 | C10: =(3/(1+('CurrentPor-Equ Factor Movements'!C10+'CurrentPor-Equ Factor Movements'!G10)/100)+103/POWER(1+('CurrentPor-Equ Factor Movements'!D10+'CurrentPor-Equ Factor Movements'!G10)/100,2))*100 -> 9614.9674 | D10: =(3/(1+('CurrentPor-Equ Factor Movements'!C10+'CurrentPor-Equ Factor Movements'!H10)/100)+103/POWER(1+('CurrentPor-Equ Factor Movements'!D10+'CurrentPor-Equ Factor Movements'!H10)/100,2))*100 -> 9601.2396 | E10: =(3/(1+('CurrentPor-Equ Factor Movements'!C10+'CurrentPor-Equ Factor Movements'!I10)/100)+103/POWER(1+('CurrentPor-Equ Factor Movements'!D10+'CurrentPor-Equ Factor Movements'!I10)/100,2))*100 -> 9581.4547 | F10: =Portfolio!B$5*'CurrentPor-Equ Factor Movements'!E10 -> 51582.192 | G10: =Portfolio!B$6*'CurrentPor-Equ Factor Movements'!F10 -> 3511.2746 | H10: =Portfolio!B$7*'CurrentPor-Equ Factor Movements'!J10 -> 2148.0999 | I10: =SUM(B10:H10) -> 95746.814
A11: 45484 | B11: =(3/(1+('CurrentPor-Equ Factor Movements'!C11)/100)+103/POWER(1+('CurrentPor-Equ Factor Movements'!D11)/100,2))*100 -> 9707.5858 | C11: =(3/(1+('CurrentPor-Equ Factor Movements'!C11+'CurrentPor-Equ Factor Movements'!G11)/100)+103/POWER(1+('CurrentPor-Equ Factor Movements'!D11+'CurrentPor-Equ Factor Movements'!G11)/100,2))*100 -> 9614.9674 | D11: =(3/(1+('CurrentPor-Equ Factor Movements'!C11+'CurrentPor-Equ Factor Movements'!H11)/100)+103/POWER(1+('CurrentPor-Equ Factor Movements'!D11+'CurrentPor-Equ Factor Movements'!H11)/100,2))*100 -> 9601.2396 | E11: =(3/(1+('CurrentPor-Equ Factor Movements'!C11+'CurrentPor-Equ Factor Movements'!I11)/100)+103/POWER(1+('CurrentPor-Equ Factor Movements'!D11+'CurrentPor-Equ Factor Movements'!I11)/100,2))*100 -> 9581.4547 | F11: =Portfolio!B$5*'CurrentPor-Equ Factor Movements'!E11 -> 52918.295 | G11: =Portfolio!B$6*'CurrentPor-Equ Factor Movements'!F11 -> 3586.6392 | H11: =Portfolio!B$7*'CurrentPor-Equ Factor Movements'!J11 -> 2148.0999 | I11: =SUM(B11:H11) -> 97158.281
A12: 45485 | B12: =(3/(1+('CurrentPor-Equ Factor Movements'!C12)/100)+103/POWER(1+('CurrentPor-Equ Factor Movements'!D12)/100,2))*100 -> 9707.5858 | C12: =(3/(1+('CurrentPor-Equ Factor Movements'!C12+'CurrentPor-Equ Factor Movements'!G12)/100)+103/POWER(1+('CurrentPor-Equ Factor Movements'!D12+'CurrentPor-Equ Factor Movements'!G12)/100,2))*100 -> 9614.9674 | D12: =(3/(1+('CurrentPor-Equ Factor Movements'!C12+'CurrentPor-Equ Factor Movements'!H12)/100)+103/POWER(1+('CurrentPor-Equ Factor Movements'!D12+'CurrentPor-Equ Factor Movements'!H12)/100,2))*100 -> 9601.2396 | E12: =(3/(1+('CurrentPor-Equ Factor Movements'!C12+'CurrentPor-Equ Factor Movements'!I12)/100)+103/POWER(1+('CurrentPor-Equ Factor Movements'!D12+'CurrentPor-Equ Factor Movements'!I12)/100,2))*100 -> 9581.4547 | F12: =Portfolio!B$5*'CurrentPor-Equ Factor Movements'!E12 -> 52877.176 | G12: =Portfolio!B$6*'CurrentPor-Equ Factor Movements'!F12 -> 3484.045 | H12: =Portfolio!B$7*'CurrentPor-Equ Factor Movements'!J12 -> 2148.0999 | I12: =SUM(B12:H12) -> 97014.568
A13: 45488 | B13: =(3/(1+('CurrentPor-Equ Factor Movements'!C13)/100)+103/POWER(1+('CurrentPor-Equ Factor Movements'!D13)/100,2))*100 -> 9707.5858 | C13: =(3/(1+('CurrentPor-Equ Factor Movements'!C13+'CurrentPor-Equ Factor Movements'!G13)/100)+103/POWER(1+('CurrentPor-Equ Factor Movements'!D13+'CurrentPor-Equ Factor Movements'!G13)/100,2))*100 -> 9614.9674 | D13: =(3/(1+('CurrentPor-Equ Factor Movements'!C13+'CurrentPor-Equ Factor Movements'!H13)/100)+103/POWER(1+('CurrentPor-Equ Factor Movements'!D13+'CurrentPor-Equ Factor Movements'!H13)/100,2))*100 -> 9601.2396 | E13: =(3/(1+('CurrentPor-Equ Factor Movements'!C13+'CurrentPor-Equ Factor Movements'!I13)/100)+103/POWER(1+('CurrentPor-Equ Factor Movements'!D13+'CurrentPor-Equ Factor Movements'!I13)/100,2))*100 -> 9581.4547 | F13: =Portfolio!B$5*'CurrentPor-Equ Factor Movements'!E13 -> 50946.564 | G13: =Portfolio!B$6*'CurrentPor-Equ Factor Movements'!F13 -> 3881.2221 | H13: =Portfolio!B$7*'CurrentPor-Equ Factor Movements'!J13 -> 2148.0999 | I13: =SUM(B13:H13) -> 95481.134 | J13: =I13-I3 -> -2027.5552
A14: 45489 | B14: =(3/(1+('CurrentPor-Equ Factor Movements'!C14)/100)+103/POWER(1+('CurrentPor-Equ Factor Movements'!D14)/100,2))*100 -> 9707.5858 | C14: =(3/(1+('CurrentPor-Equ Factor Movements'!C14+'CurrentPor-Equ Factor Movements'!G14)/100)+103/POWER(1+('CurrentPor-Equ Factor Movements'!D14+'CurrentPor-Equ Factor Movements'!G14)/100,2))*100 -> 9614.9674 | D14: =(3/(1+('CurrentPor-Equ Factor Movements'!C14+'CurrentPor-Equ Factor Movements'!H14)/100)+103/POWER(1+('CurrentPor-Equ Factor Movements'!D14+'CurrentPor-Equ Factor Movements'!H14)/100,2))*100 -> 9601.2396 | E14: =(3/(1+('CurrentPor-Equ Factor Movements'!C14+'CurrentPor-Equ Factor Movements'!I14)/100)+103/POWER(1+('CurrentPor-Equ Factor Movements'!D14+'CurrentPor-Equ Factor Movements'!I14)/100,2))*100 -> 9581.4547 | F14: =Portfolio!B$5*'CurrentPor-Equ Factor Movements'!E14 -> 54408.626 | G14: =Portfolio!B$6*'CurrentPor-Equ Factor Movements'!F14 -> 3656.6971 | H14: =Portfolio!B$7*'CurrentPor-Equ Factor Movements'!J14 -> 2148.0999 | I14: =SUM(B14:H14) -> 98718.671 | J14: =I14-I4 -> 2229.9376
A15: 45490 | B15: =(3/(1+('CurrentPor-Equ Factor Movements'!C15)/100)+103/POWER(1+('CurrentPor-Equ Factor Movements'!D15)/100,2))*100 -> 9707.5858 | C15: =(3/(1+('CurrentPor-Equ Factor Movements'!C15+'CurrentPor-Equ Factor Movements'!G15)/100)+103/POWER(1+('CurrentPor-Equ Factor Movements'!D15+'CurrentPor-Equ Factor Movements'!G15)/100,2))*100 -> 9614.9674 | D15: =(3/(1+('CurrentPor-Equ Factor Movements'!C15+'CurrentPor-Equ Factor Movements'!H15)/100)+103/POWER(1+('CurrentPor-Equ Factor Movements'!D15+'CurrentPor-Equ Factor Movements'!H15)/100,2))*100 -> 9601.2396 | E15: =(3/(1+('CurrentPor-Equ Factor Movements'!C15+'CurrentPor-Equ Factor Movements'!I15)/100)+103/POWER(1+('CurrentPor-Equ Factor Movements'!D15+'CurrentPor-Equ Factor Movements'!I15)/100,2))*100 -> 9581.4547 | F15: =Portfolio!B$5*'CurrentPor-Equ Factor Movements'!E15 -> 53948.766 | G15: =Portfolio!B$6*'CurrentPor-Equ Factor Movements'!F15 -> 3392.1065 | H15: =Portfolio!B$7*'CurrentPor-Equ Factor Movements'!J15 -> 2148.0999 | I15: =SUM(B15:H15) -> 97994.22 | J15: =I15-I5 -> 2691.1361
A16: 45491 | B16: =(3/(1+('CurrentPor-Equ Factor Movements'!C16)/100)+103/POWER(1+('CurrentPor-Equ Factor Movements'!D16)/100,2))*100 -> 9707.5858 | C16: =(3/(1+('CurrentPor-Equ Factor Movements'!C16+'CurrentPor-Equ Factor Movements'!G16)/100)+103/POWER(1+('CurrentPor-Equ Factor Movements'!D16+'CurrentPor-Equ Factor Movements'!G16)/100,2))*100 -> 9614.9674 | D16: =(3/(1+('CurrentPor-Equ Factor Movements'!C16+'CurrentPor-Equ Factor Movements'!H16)/100)+103/POWER(1+('CurrentPor-Equ Factor Movements'!D16+'CurrentPor-Equ Factor Movements'!H16)/100,2))*100 -> 9601.2396 | E16: =(3/(1+('CurrentPor-Equ Factor Movements'!C16+'CurrentPor-Equ Factor Movements'!I16)/100)+103/POWER(1+('CurrentPor-Equ Factor Movements'!D16+'CurrentPor-Equ Factor Movements'!I16)/100,2))*100 -> 9581.4547 | F16: =Portfolio!B$5*'CurrentPor-Equ Factor Movements'!E16 -> 52647.21 | G16: =Portfolio!B$6*'CurrentPor-Equ Factor Movements'!F16 -> 3870.626 | H16: =Portfolio!B$7*'CurrentPor-Equ Factor Movements'!J16 -> 2148.0999 | I16: =SUM(B16:H16) -> 97171.183 | J16: =I16-I6 -> 1235.0405
A17: 45492 | B17: =(3/(1+('CurrentPor-Equ Factor Movements'!C17)/100)+103/POWER(1+('CurrentPor-Equ Factor Movements'!D17)/100,2))*100 -> 9707.5858 | C17: =(3/(1+('CurrentPor-Equ Factor Movements'!C17+'CurrentPor-Equ Factor Movements'!G17)/100)+103/POWER(1+('CurrentPor-Equ Factor Movements'!D17+'CurrentPor-Equ Factor Movements'!G17)/100,2))*100 -> 9614.9674 | D17: =(3/(1+('CurrentPor-Equ Factor Movements'!C17+'CurrentPor-Equ Factor Movements'!H17)/100)+103/POWER(1+('CurrentPor-Equ Factor Movements'!D17+'CurrentPor-Equ Factor Movements'!H17)/100,2))*100 -> 9601.2396 | E17: =(3/(1+('CurrentPor-Equ Factor Movements'!C17+'CurrentPor-Equ Factor Movements'!I17)/100)+103/POWER(1+('CurrentPor-Equ Factor Movements'!D17+'CurrentPor-Equ Factor Movements'!I17)/100,2))*100 -> 9581.4547 | F17: =Portfolio!B$5*'CurrentPor-Equ Factor Movements'!E17 -> 52006.071 | G17: =Portfolio!B$6*'CurrentPor-Equ Factor Movements'!F17 -> 3649.8394 | H17: =Portfolio!B$7*'CurrentPor-Equ Factor Movements'!J17 -> 2148.0999 | I17: =SUM(B17:H17) -> 96309.258 | J17: =I17-I7 -> 904.21985
A18: 45495 | B18: =(3/(1+('CurrentPor-Equ Factor Movements'!C18)/100)+103/POWER(1+('CurrentPor-Equ Factor Movements'!D18)/100,2))*100 -> 9707.5858 | C18: =(3/(1+('CurrentPor-Equ Factor Movements'!C18+'CurrentPor-Equ Factor Movements'!G18)/100)+103/POWER(1+('CurrentPor-Equ Factor Movements'!D18+'CurrentPor-Equ Factor Movements'!G18)/100,2))*100 -> 9614.9674 | D18: =(3/(1+('CurrentPor-Equ Factor Movements'!C18+'CurrentPor-Equ Factor Movements'!H18)/100)+103/POWER(1+('CurrentPor-Equ Factor Movements'!D18+'CurrentPor-Equ Factor Movements'!H18)/100,2))*100 -> 9601.2396 | E18: =(3/(1+('CurrentPor-Equ Factor Movements'!C18+'CurrentPor-Equ Factor Movements'!I18)/100)+103/POWER(1+('CurrentPor-Equ Factor Movements'!D18+'CurrentPor-Equ Factor Movements'!I18)/100,2))*100 -> 9581.4547 | F18: =Portfolio!B$5*'CurrentPor-Equ Factor Movements'!E18 -> 52195.677 | G18: =Portfolio!B$6*'CurrentPor-Equ Factor Movements'!F18 -> 3504.6739 | H18: =Portfolio!B$7*'CurrentPor-Equ Factor Movements'!J18 -> 2148.0999 | I18: =SUM(B18:H18) -> 96353.698 | J18: =I18-I8 -> 584.19435
A19: 45496 | B19: =(3/(1+('CurrentPor-Equ Factor Movements'!C19)/100)+103/POWER(1+('CurrentPor-Equ Factor Movements'!D19)/100,2))*100 -> 9707.5858 | C19: =(3/(1+('CurrentPor-Equ Factor Movements'!C19+'CurrentPor-Equ Factor Movements'!G19)/100)+103/POWER(1+('CurrentPor-Equ Factor Movements'!D19+'CurrentPor-Equ Factor Movements'!G19)/100,2))*100 -> 9614.9674 | D19: =(3/(1+('CurrentPor-Equ Factor Movements'!C19+'CurrentPor-Equ Factor Movements'!H19)/100)+103/POWER(1+('CurrentPor-Equ Factor Movements'!D19+'CurrentPor-Equ Factor Movements'!H19)/100,2))*100 -> 9601.2396 | E19: =(3/(1+('CurrentPor-Equ Factor Movements'!C19+'CurrentPor-Equ Factor Movements'!I19)/100)+103/POWER(1+('CurrentPor-Equ Factor Movements'!D19+'CurrentPor-Equ Factor Movements'!I19)/100,2))*100 -> 9581.4547 | F19: =Portfolio!B$5*'CurrentPor-Equ Factor Movements'!E19 -> 52357.378 | G19: =Portfolio!B$6*'CurrentPor-Equ Factor Movements'!F19 -> 3703.6454 | H19: =Portfolio!B$7*'CurrentPor-Equ Factor Movements'!J19 -> 2148.0999 | I19: =SUM(B19:H19) -> 96714.371 | J19: =I19-I9 -> 501.47165
A20: 45497 | B20: =(3/(1+('CurrentPor-Equ Factor Movements'!C20)/100)+103/POWER(1+('CurrentPor-Equ Factor Movements'!D20)/100,2))*100 -> 9707.5858 | C20: =(3/(1+('CurrentPor-Equ Factor Movements'!C20+'CurrentPor-Equ Factor Movements'!G20)/100)+103/POWER(1+('CurrentPor-Equ Factor Movements'!D20+'CurrentPor-Equ Factor Movements'!G20)/100,2))*100 -> 9614.9674 | D20: =(3/(1+('CurrentPor-Equ Factor Movements'!C20+'CurrentPor-Equ Factor Movements'!H20)/100)+103/POWER(1+('CurrentPor-Equ Factor Movements'!D20+'CurrentPor-Equ Factor Movements'!H20)/100,2))*100 -> 9601.2396 | E20: =(3/(1+('CurrentPor-Equ Factor Movements'!C20+'CurrentPor-Equ Factor Movements'!I20)/100)+103/POWER(1+('CurrentPor-Equ Factor Movements'!D20+'CurrentPor-Equ Factor Movements'!I20)/100,2))*100 -> 9581.4547 | F20: =Portfolio!B$5*'CurrentPor-Equ Factor Movements'!E20 -> 51942.921 | G20: =Portfolio!B$6*'CurrentPor-Equ Factor Movements'!F20 -> 3347.2186 | H20: =Portfolio!B$7*'CurrentPor-Equ Factor Movements'!J20 -> 2148.0999 | I20: =SUM(B20:H20) -> 95943.487 | J20: =I20-I10 -> 196.6732
A21: 45498 | B21: =(3/(1+('CurrentPor-Equ Factor Movements'!C21)/100)+103/POWER(1+('CurrentPor-Equ Factor Movements'!D21)/100,2))*100 -> 9707.5858 | C21: =(3/(1+('CurrentPor-Equ Factor Movements'!C21+'CurrentPor-Equ Factor Movements'!G21)/100)+103/POWER(1+('CurrentPor-Equ Factor Movements'!D21+'CurrentPor-Equ Factor Movements'!G21)/100,2))*100 -> 9614.9674 | D21: =(3/(1+('CurrentPor-Equ Factor Movements'!C21+'CurrentPor-Equ Factor Movements'!H21)/100)+103/POWER(1+('CurrentPor-Equ Factor Movements'!D21+'CurrentPor-Equ Factor Movements'!H21)/100,2))*100 -> 9601.2396 | E21: =(3/(1+('CurrentPor-Equ Factor Movements'!C21+'CurrentPor-Equ Factor Movements'!I21)/100)+103/POWER(1+('CurrentPor-Equ Factor Movements'!D21+'CurrentPor-Equ Factor Movements'!I21)/100,2))*100 -> 9581.4547 | F21: =Portfolio!B$5*'CurrentPor-Equ Factor Movements'!E21 -> 53461.004 | G21: =Portfolio!B$6*'CurrentPor-Equ Factor Movements'!F21 -> 3668.1117 | H21: =Portfolio!B$7*'CurrentPor-Equ Factor Movements'!J21 -> 2148.0999 | I21: =SUM(B21:H21) -> 97782.463 | J21: =I21-I11 -> 624.18171
A22: 45499 | B22: =(3/(1+('CurrentPor-Equ Factor Movements'!C22)/100)+103/POWER(1+('CurrentPor-Equ Factor Movements'!D22)/100,2))*100 -> 9707.5858 | C22: =(3/(1+('CurrentPor-Equ Factor Movements'!C22+'CurrentPor-Equ Factor Movements'!G22)/100)+103/POWER(1+('CurrentPor-Equ Factor Movements'!D22+'CurrentPor-Equ Factor Movements'!G22)/100,2))*100 -> 9614.9674 | D22: =(3/(1+('CurrentPor-Equ Factor Movements'!C22+'CurrentPor-Equ Factor Movements'!H22)/100)+103/POWER(1+('CurrentPor-Equ Factor Movements'!D22+'CurrentPor-Equ Factor Movements'!H22)/100,2))*100 -> 9601.2396 | E22: =(3/(1+('CurrentPor-Equ Factor Movements'!C22+'CurrentPor-Equ Factor Movements'!I22)/100)+103/POWER(1+('CurrentPor-Equ Factor Movements'!D22+'CurrentPor-Equ Factor Movements'!I22)/100,2))*100 -> 9581.4547 | F22: =Portfolio!B$5*'CurrentPor-Equ Factor Movements'!E22 -> 52396.808 | G22: =Portfolio!B$6*'CurrentPor-Equ Factor Movements'!F22 -> 3507.856 | H22: =Portfolio!B$7*'CurrentPor-Equ Factor Movements'!J22 -> 2148.0999 | I22: =SUM(B22:H22) -> 96558.011 | J22: =I22-I12 -> -456.5565
A23: 45502 | B23: =(3/(1+('CurrentPor-Equ Factor Movements'!C23)/100)+103/POWER(1+('CurrentPor-Equ Factor Movements'!D23)/100,2))*100 -> 9707.5858 | C23: =(3/(1+('CurrentPor-Equ Factor Movements'!C23+'CurrentPor-Equ Factor Movements'!G23)/100)+103/POWER(1+('CurrentPor-Equ Factor Movements'!D23+'CurrentPor-Equ Factor Movements'!G23)/100,2))*100 -> 9614.9674 | D23: =(3/(1+('CurrentPor-Equ Factor Movements'!C23+'CurrentPor-Equ Factor Movements'!H23)/100)+103/POWER(1+('CurrentPor-Equ Factor Movements'!D23+'CurrentPor-Equ Factor Movements'!H23)/100,2))*100 -> 9601.2396 | E23: =(3/(1+('CurrentPor-Equ Factor Movements'!C23+'CurrentPor-Equ Factor Movements'!I23)/100)+103/POWER(1+('CurrentPor-Equ Factor Movements'!D23+'CurrentPor-Equ Factor Movements'!I23)/100,2))*100 -> 9581.4547 | F23: =Portfolio!B$5*'CurrentPor-Equ Factor Movements'!E23 -> 51493.5 | G23: =Portfolio!B$6*'CurrentPor-Equ Factor Movements'!F23 -> 3468.3566 | H23: =Portfolio!B$7*'CurrentPor-Equ Factor Movements'!J23 -> 2148.0999 | I23: =SUM(B23:H23) -> 95615.204 | J23: =I23-I13 -> 134.07062
A24: 45503 | B24: =(3/(1+('CurrentPor-Equ Factor Movements'!C24)/100)+103/POWER(1+('CurrentPor-Equ Factor Movements'!D24)/100,2))*100 -> 9707.5858 | C24: =(3/(1+('CurrentPor-Equ Factor Movements'!C24+'CurrentPor-Equ Factor Movements'!G24)/100)+103/POWER(1+('CurrentPor-Equ Factor Movements'!D24+'CurrentPor-Equ Factor Movements'!G24)/100,2))*100 -> 9614.9674 | D24: =(3/(1+('CurrentPor-Equ Factor Movements'!C24+'CurrentPor-Equ Factor Movements'!H24)/100)+103/POWER(1+('CurrentPor-Equ Factor Movements'!D24+'CurrentPor-Equ Factor Movements'!H24)/100,2))*100 -> 9601.2396 | E24: =(3/(1+('CurrentPor-Equ Factor Movements'!C24+'CurrentPor-Equ Factor Movements'!I24)/100)+103/POWER(1+('CurrentPor-Equ Factor Movements'!D24+'CurrentPor-Equ Factor Movements'!I24)/100,2))*100 -> 9581.4547 | F24: =Portfolio!B$5*'CurrentPor-Equ Factor Movements'!E24 -> 51737.828 | G24: =Portfolio!B$6*'CurrentPor-Equ Factor Movements'!F24 -> 3669.7269 | H24: =Portfolio!B$7*'CurrentPor-Equ Factor Movements'!J24 -> 2148.0999 | I24: =SUM(B24:H24) -> 96060.902 | J24: =I24-I14 -> -2657.7686
... A263: 45838 | B263: =(3/(1+('CurrentPor-Equ Factor Movements'!C263)/100)+103/POWER(1+('CurrentPor-Equ Factor Movements'!D263)/100,2))*100 -> 9707.5858 | C263: =(3/(1+('CurrentPor-Equ Factor Movements'!C263+'CurrentPor-Equ Factor Movements'!G263)/100)+103/POWER(1+('CurrentPor-Equ Factor Movements'!D263+'CurrentPor-Equ Factor Movements'!G263)/100,2))*100 -> 9614.9674 | D263: =(3/(1+('CurrentPor-Equ Factor Movements'!C263+'CurrentPor-Equ Factor Movements'!H263)/100)+103/POWER(1+('CurrentPor-Equ Factor Movements'!D263+'CurrentPor-Equ Factor Movements'!H263)/100,2))*100 -> 9601.2396 | E263: =(3/(1+('CurrentPor-Equ Factor Movements'!C263+'CurrentPor-Equ Factor Movements'!I263)/100)+103/POWER(1+('CurrentPor-Equ Factor Movements'!D263+'CurrentPor-Equ Factor Movements'!I263)/100,2))*100 -> 9581.4547 | F263: =Portfolio!B$5*'CurrentPor-Equ Factor Movements'!E263 -> 51079.332 | G263: =Portfolio!B$6*'CurrentPor-Equ Factor Movements'!F263 -> 3615.2701 | H263: =Portfolio!B$7*'CurrentPor-Equ Factor Movements'!J263 -> 2148.0999 | I263: =SUM(B263:H263) -> 95347.949 | J263: =I263-I253 -> -1125.666

Sheet NMRF
A1: 8. 🔋 Lithium / Rare Earth Commodity Futures
A3: The Risk Factor:
A5: Lithium carbonate futures
A6: Cobalt or rare earth element derivatives
A8: Why NMRF in 2007:
A10: ❌ No lithium futures (demand was minimal - pre-EV boom)
A11: ❌ Rare earths traded OTC only
A12: ❌ China monopoly = no transparent pricing
A13: ❌ No derivatives exchanges
A15: Today:
A17: ✅ CME lithium futures launched (2021)
A18: ✅ LME cobalt futures exist
... A41: ESG/Green Bond Spreads

Sheet formulae
A1: NORM.INV(RAND(), 38, 5)
A2: FILTER(A2, WEEKDAY(A2, 2) <= 5)
